tsdistances-0.1.7.dist-info/METADATA
tsdistances-0.1.7.dist-info/WHEEL
tsdistances-0.1.7.dist-info/licenses/LICENSE
tsdistances/__init__.py
tsdistances/tsdistances.cpython-311-x86_64-linux-gnu.so
tsdistances-0.1.7.dist-info/RECORD
