Metadata-Version: 2.4
Name: tsdistances
Version: 0.1.7
Classifier: Programming Language :: Python :: 3
Classifier: Operating System :: OS Independent
Requires-Dist: numpy
Requires-Dist: typeguard
License-File: LICENSE
Summary: tsdistances is a Python library (with Rust backend) for computing various pairwise distances between sets of time series data.
Author: Alberto Azzari alberto.azzari@univr.it, Andrea Cracco andrea.cracco@univr.it, Francesco Masillo francesco.masillo@univr.it
Author-email: Alberto Azzari alberto.azzari@univr.it, Andrea Cracco andrea.cracco@univr.it, Francesco Masillo francesco.masillo@univr.it
Requires-Python: >=3.10
Project-URL: Homepage, https://github.com/albertoazzari/tsdistances
Project-URL: Issues, https://github.com/albertoazzari/tsdistances/issues
